findx/__init__.py
findx-0.12.0.dist-info/METADATA
findx-0.12.0.dist-info/WHEEL
findx-0.12.0.dist-info/entry_points.txt
findx-0.12.0.dist-info/licenses/LICENSE.rst
findx-0.12.0.dist-info/RECORD
