Metadata-Version: 2.4
Name: findx
Version: 0.12.0
Summary: ``findx``, an extended ``find`` command.
Author-email: Michael Henry <drmikehenry@drmikehenry.com>
License-Expression: MIT
License-File: LICENSE.rst
Keywords: extended,file,find,search
Classifier: Development Status :: 5 - Production/Stable
Classifier: Environment :: Console
Classifier: License :: OSI Approved :: MIT License
Classifier: Programming Language :: Python :: 3
Classifier: Programming Language :: Python :: 3 :: Only
Classifier: Programming Language :: Python :: 3.8
Classifier: Programming Language :: Python :: 3.9
Classifier: Programming Language :: Python :: 3.10
Classifier: Programming Language :: Python :: 3.11
Classifier: Programming Language :: Python :: 3.12
Classifier: Programming Language :: Python :: 3.13
Classifier: Topic :: Utilities
Requires-Python: >=3.8
